inmanta_plugins/ubuntu/__init__.py
inmanta_plugins/ubuntu/setup.cfg
inmanta_plugins/ubuntu/model/_init.cf
inmanta_module_ubuntu-0.4.21.dist-info/METADATA
inmanta_module_ubuntu-0.4.21.dist-info/WHEEL
inmanta_module_ubuntu-0.4.21.dist-info/top_level.txt
inmanta_module_ubuntu-0.4.21.dist-info/RECORD
