Metadata-Version: 2.1
Name: inmanta-module-ubuntu
Version: 0.4.21
License: Apache 2.0
Requires-Dist: inmanta-module-apt
Requires-Dist: inmanta-module-std
